{"strategy":{"Heracles":{"trades":[{"pair":"BTC/USDT","stake_amount":955.2774,"amount":0.022,"open_date":"2022-01-06 00:00:00+00:00","close_date":"2022-01-12 12:00:00+00:00","open_rate":43421.7,"close_rate":43439.07215443088,"fee_open":0.0002,"fee_close":0.0002,"trade_duration":9360,"profit_ratio":-0.0017106814574834634,"profit_abs":-1.63450217,"exit_reason":"roi","initial_stop_loss_abs":32305.8,"initial_stop_loss_ratio":-0.256,"stop_loss_abs":32305.8,"stop_loss_ratio":-0.256,"min_rate":39610.0,"max_rate":44091.93,"is_open":false,"enter_tag":null,"leverage":1.0,"is_short":false,"open_timestamp":1641427200000,"close_timestamp":1641988800000,"orders":[{"amount":0.022,"safe_price":43421.7,"ft_order_side":"buy","order_filled_timestamp":1641427200000,"ft_is_entry":true},{"amount":0.022,"safe_price":43439.07215443088,"ft_order_side":"sell","order_filled_timestamp":1641988800000,"ft_is_entry":false}]},{"pair":"BTC/USDT","stake_amount":961.59756,"amount":0.022,"open_date":"2022-01-12 20:00:00+00:00","close_date":"2022-02-07 12:00:00+00:00","open_rate":43708.98,"close_rate":43726.467089417885,"fee_open":0.0002,"fee_close":0.0002,"trade_duration":36960,"profit_ratio":-0.002268819350757968,"profit_abs":-2.18212749,"exit_reason":"roi","initial_stop_loss_abs":32519.5,"initial_stop_loss_ratio":-0.256,"stop_loss_abs":32519.5,"stop_loss_ratio":-0.256,"min_rate":32853.83,"max_rate":44396.68,"is_open":false,"enter_tag":null,"leverage":1.0,"is_short":false,"open_timestamp":1642017600000,"close_timestamp":1644235200000,"orders":[{"amount":0.022,"safe_price":43708.98,"ft_order_side":"buy","order_filled_timestamp":1642017600000,"ft_is_entry":true},{"amount":0.022,"safe_price":43726.467089417885,"ft_order_side":"sell","order_filled_timestamp":1644235200000,"ft_is_entry":false}]},{"pair":"BTC/USDT","stake_amount":963.71572,"amount":0.022,"open_date":"2022-02-07 16:00:00+00:00","close_date":"2022-02-15 08:00:00+00:00","open_rate":43805.26,"close_rate":43822.78560912183,"fee_open":0.0002,"fee_close":0.0002,"trade_duration":11040,"profit_ratio":-0.001206408527846152,"profit_abs":-1.16286739,"exit_reason":"roi","initial_stop_loss_abs":32591.2,"initial_stop_loss_ratio":-0.256,"stop_loss_abs":32591.2,"stop_loss_ratio":-0.256,"min_rate":41526.0,"max_rate":45847.5,"is_open":false,"enter_tag":null,"leverage":1.0,"is_short":false,"open_timestamp":1644249600000,"close_timestamp":1644912000000,"orders":[{"amount":0.022,"safe_price":43805.26,"ft_order_side":"buy","order_filled_timestamp":1644249600000,"ft_is_entry":true},{"amount":0.022,"safe_price":43822.78560912183,"ft_order_side":"sell","order_filled_timestamp":1644912000000,"ft_is_entry":false}]},{"pair":"BTC/USDT","stake_amount":979.6534,"amount":0.022,"open_date":"2022-02-16 00:00:00+00:00","close_date":"2022-03-01 12:00:00+00:00","open_rate":44529.7,"close_rate":44547.51544308861,"fee_open":0.0002,"fee_close":0.0002,"trade_duration":19440,"profit_ratio":-0.0006996485771177074,"profit_abs":-0.68555019,"exit_reason":"roi","initial_stop_loss_abs":33130.1,"initial_stop_loss_ratio":-0.256,"stop_loss_abs":33130.1,"stop_loss_ratio":-0.256,"min_rate":34303.7,"max_rate":44935.0,"is_open":false,"enter_tag":null,"leverage":1.0,"is_short":false,"open_timestamp":1644969600000,"close_timestamp":1646136000000,"orders":[{"amount":0.022,"safe_price":44529.7,"ft_order_side":"buy","order_filled_timestamp":1644969600000,"ft_is_entry":true},{"amount":0.022,"safe_price":44547.51544308861,"ft_order_side":"sell","order_filled_timestamp":1646136000000,"ft_is_entry":false}]},{"pair":"BTC/USDT","stake_amount":952.8816,"amount":0.022,"open_date":"2022-03-03 04:00:00+00:00","close_date":"2022-03-22 04:00:00+00:00","open_rate":43312.8,"close_rate":43330.12858571714,"fee_open":0.0002,"fee_close":0.0002,"trade_duration":27360,"profit_ratio":-0.002503784749245254,"profit_abs":-2.38628758,"exit_reason":"roi","initial_stop_loss_abs":32224.8,"initial_stop_loss_ratio":-0.256,"stop_loss_abs":32224.8,"stop_loss_ratio":-0.256,"min_rate":37134.0,"max_rate":44080.0,"is_open":false,"enter_tag":null,"leverage":1.0,"is_short":false,"open_timestamp":1646280000000,"close_timestamp":1647921600000,"orders":[{"amount":0.022,"safe_price":43312.8,"ft_order_side":"buy","order_filled_timestamp":1646280000000,"ft_is_entry":true},{"amount":0.022,"safe_price":43330.12858571714,"ft_order_side":"sell","order_filled_timestamp":1647921600000,"ft_is_entry":false}]},{"pair":"BTC/USDT","stake_amount":970.554,"amount":0.023,"open_date":"2022-03-22 08:00:00+00:00","close_date":"2022-03-27 12:00:00+00:00","open_rate":42198.0,"close_rate":44416.0,"fee_open":0.0002,"fee_close":0.0002,"trade_duration":7440,"profit_ratio":0.05143362743075863,"profit_abs":49.92909666,"exit_reason":"roi","initial_stop_loss_abs":31395.4,"initial_stop_loss_ratio":-0.256,"stop_loss_abs":31395.4,"stop_loss_ratio":-0.256,"min_rate":41731.3,"max_rate":45142.0,"is_open":false,"enter_tag":null,"leverage":1.0,"is_short":false,"open_timestamp":1647936000000,"close_timestamp":1648382400000,"orders":[{"amount":0.023,"safe_price":42198.0,"ft_order_side":"buy","order_filled_timestamp":1647936000000,"ft_is_entry":true},{"amount":0.023,"safe_price":44416.0,"ft_order_side":"sell","order_filled_timestamp":1648382400000,"ft_is_entry":false}]},{"pair":"BTC/USDT","stake_amount":1031.2303,"amount":0.023,"open_date":"2022-03-27 16:00:00+00:00","close_date":"2022-04-01 20:00:00+00:00","open_rate":44836.1,"close_rate":46056.6,"fee_open":0.0002,"fee_close":0.0002,"trade_duration":7440,"profit_ratio":0.02518004201926853,"profit_abs":25.97161557,"exit_reason":"roi","initial_stop_loss_abs":33358.1,"initial_stop_loss_ratio":-0.256,"stop_loss_abs":33358.1,"stop_loss_ratio":-0.256,"min_rate":44206.2,"max_rate":48200.0,"is_open":false,"enter_tag":null,"leverage":1.0,"is_short":false,"open_timestamp":1648396800000,"close_timestamp":1648843200000,"orders":[{"amount":0.023,"safe_price":44836.1,"ft_order_side":"buy","order_filled_timestamp":1648396800000,"ft_is_entry":true},{"amount":0.023,"safe_price":46056.6,"ft_order_side":"sell","order_filled_timestamp":1648843200000,"ft_is_entry":false}]},{"pair":"BTC/USDT","stake_amount":1017.8564,"amount":0.022,"open_date":"2022-04-02 00:00:00+00:00","close_date":"2022-05-08 00:00:00+00:00","open_rate":46266.2,"close_rate":34422.1,"fee_open":0.0002,"fee_close":0.0002,"trade_duration":51840,"profit_ratio":-0.2594192790115727,"profit_abs":-264.10438374,"exit_reason":"stop_loss","initial_stop_loss_abs":34422.1,"initial_stop_loss_ratio":-0.256,"stop_loss_abs":34422.1,"stop_loss_ratio":-0.256,"min_rate":34150.0,"max_rate":47448.0,"is_open":false,"enter_tag":null,"leverage":1.0,"is_short":false,"open_timestamp":1648857600000,"close_timestamp":1651968000000,"orders":[{"amount":0.022,"safe_price":46266.2,"ft_order_side":"buy","order_filled_timestamp":1648857600000,"ft_is_entry":true},{"amount":0.022,"safe_price":34422.1,"ft_order_side":"sell","order_filled_timestamp":1651968000000,"ft_is_entry":false}]},{"pair":"BTC/USDT","stake_amount":791.362,"amount":0.026,"open_date":"2022-05-18 00:00:00+00:00","close_date":"2022-05-23 04:00:00+00:00","open_rate":30437.0,"close_rate":30449.17723544709,"fee_open":0.0002,"fee_close":0.0002,"trade_duration":7440,"profit_ratio":-0.0005146463384504971,"profit_abs":-0.40735301,"exit_reason":"roi","initial_stop_loss_abs":22645.2,"initial_stop_loss_ratio":-0.256,"stop_loss_abs":22645.2,"stop_loss_ratio":-0.256,"min_rate":28629.6,"max_rate":30784.4,"is_open":false,"enter_tag":null,"leverage":1.0,"is_short":false,"open_timestamp":1652832000000,"close_timestamp":1653278400000,"orders":[{"amount":0.026,"safe_price":30437.0,"ft_order_side":"buy","order_filled_timestamp":1652832000000,"ft_is_entry":true},{"amount":0.026,"safe_price":30449.17723544709,"ft_order_side":"sell","order_filled_timestamp":1653278400000,"ft_is_entry":false}]},{"pair":"BTC/USDT","stake_amount":793.2276,"amount":0.027,"open_date":"2022-05-24 20:00:00+00:00","close_date":"2022-05-30 00:00:00+00:00","open_rate":29378.8,"close_rate":29390.55387077415,"fee_open":0.0002,"fee_close":0.0002,"trade_duration":7440,"profit_ratio":-0.0013977011276181065,"profit_abs":-1.10891685,"exit_reason":"roi","initial_stop_loss_abs":21857.9,"initial_stop_loss_ratio":-0.256,"stop_loss_abs":21857.9,"stop_loss_ratio":-0.256,"min_rate":27952.1,"max_rate":30448.0,"is_open":false,"enter_tag":null,"leverage":1.0,"is_short":false,"open_timestamp":1653422400000,"close_timestamp":1653868800000,"orders":[{"amount":0.027,"safe_price":29378.8,"ft_order_side":"buy","order_filled_timestamp":1653422400000,"ft_is_entry":true},{"amount":0.027,"safe_price":29390.55387077415,"ft_order_side":"sell","order_filled_timestamp":1653868800000,"ft_is_entry":false}]},{"pair":"BTC/USDT","stake_amount":794.0825,"amount":0.025,"open_date":"2022-05-31 04:00:00+00:00","close_date":"2022-06-13 08:00:00+00:00","open_rate":31763.3,"close_rate":23631.9,"fee_open":0.0002,"fee_close":0.0002,"trade_duration":18960,"profit_ratio":-0.2582521883700065,"profit_abs":-205.11455808,"exit_reason":"stop_loss","initial_stop_loss_abs":23631.9,"initial_stop_loss_ratio":-0.256,"stop_loss_abs":23631.9,"stop_loss_ratio":-0.256,"min_rate":23464.3,"max_rate":32427.5,"is_open":false,"enter_tag":null,"leverage":1.0,"is_short":false,"open_timestamp":1653969600000,"close_timestamp":1655107200000,"orders":[{"amount":0.025,"safe_price":31763.3,"ft_order_side":"buy","order_filled_timestamp":1653969600000,"ft_is_entry":true},{"amount":0.025,"safe_price":23631.9,"ft_order_side":"sell","order_filled_timestamp":1655107200000,"ft_is_entry":false}]},{"pair":"BTC/USDT","stake_amount":577.5327,"amount":0.027,"open_date":"2022-06-26 08:00:00+00:00","close_date":"2022-07-07 16:00:00+00:00","open_rate":21390.1,"close_rate":21398.657751550305,"fee_open":0.0002,"fee_close":0.0002,"trade_duration":16320,"profit_ratio":-0.0010455033412419673,"profit_abs":-0.60393313,"exit_reason":"roi","initial_stop_loss_abs":15914.3,"initial_stop_loss_ratio":-0.256,"stop_loss_abs":15914.3,"stop_loss_ratio":-0.256,"min_rate":18563.0,"max_rate":21888.0,"is_open":false,"enter_tag":null,"leverage":1.0,"is_short":false,"open_timestamp":1656230400000,"close_timestamp":1657209600000,"orders":[{"amount":0.027,"safe_price":21390.1,"ft_order_side":"buy","order_filled_timestamp":1656230400000,"ft_is_entry":true},{"amount":0.027,"safe_price":21398.657751550305,"ft_order_side":"sell","order_filled_timestamp":1657209600000,"ft_is_entry":false}]},{"pair":"BTC/USDT","stake_amount":588.5433,"amount":0.027,"open_date":"2022-07-07 20:00:00+00:00","close_date":"2022-07-18 04:00:00+00:00","open_rate":21797.9,"close_rate":21806.620904180836,"fee_open":0.0002,"fee_close":0.0002,"trade_duration":14880,"profit_ratio":-0.001822499595212106,"profit_abs":-1.07283445,"exit_reason":"roi","initial_stop_loss_abs":16217.7,"initial_stop_loss_ratio":-0.256,"stop_loss_abs":16217.7,"stop_loss_ratio":-0.256,"min_rate":18901.0,"max_rate":22579.9,"is_open":false,"enter_tag":null,"leverage":1.0,"is_short":false,"open_timestamp":1657224000000,"close_timestamp":1658116800000,"orders":[{"amount":0.027,"safe_price":21797.9,"ft_order_side":"buy","order_filled_timestamp":1657224000000,"ft_is_entry":true},{"amount":0.027,"safe_price":21806.620904180836,"ft_order_side":"sell","order_filled_timestamp":1658116800000,"ft_is_entry":false}]},{"pair":"BTC/USDT","stake_amount":578.3258,"amount":0.026,"open_date":"2022-07-18 08:00:00+00:00","close_date":"2022-07-23 12:00:00+00:00","open_rate":22243.3,"close_rate":22252.19909981996,"fee_open":0.0002,"fee_close":0.0002,"trade_duration":7440,"profit_ratio":-0.0014767576867327772,"profit_abs":-0.85421788,"exit_reason":"roi","initial_stop_loss_abs":16549.1,"initial_stop_loss_ratio":-0.256,"stop_loss_abs":16549.1,"stop_loss_ratio":-0.256,"min_rate":21385.7,"max_rate":24277.0,"is_open":false,"enter_tag":null,"leverage":1.0,"is_short":false,"open_timestamp":1658131200000,"close_timestamp":1658577600000,"orders":[{"amount":0.026,"safe_price":22243.3,"ft_order_side":"buy","order_filled_timestamp":1658131200000,"ft_is_entry":true},{"amount":0.026,"safe_price":22252.19909981996,"ft_order_side":"sell","order_filled_timestamp":1658577600000,"ft_is_entry":false}]},{"pair":"BTC/USDT","stake_amount":586.8356,"amount":0.026,"open_date":"2022-07-25 00:00:00+00:00","close_date":"2022-07-30 04:00:00+00:00","open_rate":22570.6,"close_rate":23621.8,"fee_open":0.0002,"fee_close":0.0002,"trade_duration":7440,"profit_ratio":0.044969687263892194,"profit_abs":26.39509137,"exit_reason":"roi","initial_stop_loss_abs":16792.6,"initial_stop_loss_ratio":-0.256,"stop_loss_abs":16792.6,"stop_loss_ratio":-0.256,"min_rate":20689.6,"max_rate":24500.0,"is_open":false,"enter_tag":null,"leverage":1.0,"is_short":false,"open_timestamp":1658707200000,"close_timestamp":1659153600000,"orders":[{"amount":0.026,"safe_price":22570.6,"ft_order_side":"buy","order_filled_timestamp":1658707200000,"ft_is_entry":true},{"amount":0.026,"safe_price":23621.8,"ft_order_side":"sell","order_filled_timestamp":1659153600000,"ft_is_entry":false}]},{"pair":"BTC/USDT","stake_amount":596.745,"amount":0.025,"open_date":"2022-07-30 08:00:00+00:00","close_date":"2022-08-08 08:00:00+00:00","open_rate":23869.8,"close_rate":23879.34982996599,"fee_open":0.0002,"fee_close":0.0002,"trade_duration":12960,"profit_ratio":-0.0015928681644210585,"profit_abs":-0.95072622,"exit_reason":"roi","initial_stop_loss_abs":17759.2,"initial_stop_loss_ratio":-0.256,"stop_loss_abs":17759.2,"stop_loss_ratio":-0.256,"min_rate":22370.0,"max_rate":24700.0,"is_open":false,"enter_tag":null,"leverage":1.0,"is_short":false,"open_timestamp":1659168000000,"close_timestamp":1659945600000,"orders":[{"amount":0.025,"safe_price":23869.8,"ft_order_side":"buy","order_filled_timestamp":1659168000000,"ft_is_entry":true},{"amount":0.025,"safe_price":23879.34982996599,"ft_order_side":"sell","order_filled_timestamp":1659945600000,"ft_is_entry":false}]},{"pair":"BTC/USDT","stake_amount":603.9975,"amount":0.025,"open_date":"2022-08-08 12:00:00+00:00","close_date":"2022-08-13 16:00:00+00:00","open_rate":24159.9,"close_rate":24321.6,"fee_open":0.0002,"fee_close":0.0002,"trade_duration":7440,"profit_ratio":0.005468612360748393,"profit_abs":3.3036888,"exit_reason":"roi","initial_stop_loss_abs":17975.0,"initial_stop_loss_ratio":-0.256,"stop_loss_abs":17975.0,"stop_loss_ratio":-0.256,"min_rate":22608.0,"max_rate":24972.0,"is_open":false,"enter_tag":null,"leverage":1.0,"is_short":false,"open_timestamp":1659960000000,"close_timestamp":1660406400000,"orders":[{"amount":0.025,"safe_price":24159.9,"ft_order_side":"buy","order_filled_timestamp":1659960000000,"ft_is_entry":true},{"amount":0.025,"safe_price":24321.6,"ft_order_side":"sell","order_filled_timestamp":1660406400000,"ft_is_entry":false}]},{"pair":"BTC/USDT","stake_amount":609.73,"amount":0.025,"open_date":"2022-08-13 20:00:00+00:00","close_date":"2022-09-21 20:00:00+00:00","open_rate":24389.2,"close_rate":18145.6,"fee_open":0.0002,"fee_close":0.0002,"trade_duration":56160,"profit_ratio":-0.25830675142258214,"profit_abs":-157.52887502,"exit_reason":"stop_loss","initial_stop_loss_abs":18145.6,"initial_stop_loss_ratio":-0.256,"stop_loss_abs":18145.6,"stop_loss_ratio":-0.256,"min_rate":18084.3,"max_rate":25200.0,"is_open":false,"enter_tag":null,"leverage":1.0,"is_short":false,"open_timestamp":1660420800000,"close_timestamp":1663790400000,"orders":[{"amount":0.025,"safe_price":24389.2,"ft_order_side":"buy","order_filled_timestamp":1660420800000,"ft_is_entry":true},{"amount":0.025,"safe_price":18145.6,"ft_order_side":"sell","order_filled_timestamp":1663790400000,"ft_is_entry":false}]},{"pair":"BTC/USDT","stake_amount":454.1712,"amount":0.024,"open_date":"2022-09-22 08:00:00+00:00","close_date":"2022-09-27 12:00:00+00:00","open_rate":18923.8,"close_rate":19860.4,"fee_open":0.0002,"fee_close":0.0002,"trade_duration":7440,"profit_ratio":0.04863128325694173,"profit_abs":22.09134566,"exit_reason":"roi","initial_stop_loss_abs":14079.4,"initial_stop_loss_ratio":-0.256,"stop_loss_abs":14079.4,"stop_loss_ratio":-0.256,"min_rate":18518.5,"max_rate":20375.0,"is_open":false,"enter_tag":null,"leverage":1.0,"is_short":false,"open_timestamp":1663833600000,"close_timestamp":1664280000000,"orders":[{"amount":0.024,"safe_price":18923.8,"ft_order_side":"buy","order_filled_timestamp":1663833600000,"ft_is_entry":true},{"amount":0.024,"safe_price":19860.4,"ft_order_side":"sell","order_filled_timestamp":1664280000000,"ft_is_entry":false}]},{"pair":"BTC/USDT","stake_amount":477.2472,"amount":0.024,"open_date":"2022-09-27 16:00:00+00:00","close_date":"2022-10-04 04:00:00+00:00","open_rate":19885.3,"close_rate":19893.25571114223,"fee_open":0.0002,"fee_close":0.0002,"trade_duration":9360,"profit_ratio":-0.001289333376604891,"profit_abs":-0.61545381,"exit_reason":"roi","initial_stop_loss_abs":14794.7,"initial_stop_loss_ratio":-0.256,"stop_loss_abs":14794.7,"stop_loss_ratio":-0.256,"min_rate":18460.0,"max_rate":20172.7,"is_open":false,"enter_tag":null,"leverage":1.0,"is_short":false,"open_timestamp":1664294400000,"close_timestamp":1664856000000,"orders":[{"amount":0.024,"safe_price":19885.3,"ft_order_side":"buy","order_filled_timestamp":1664294400000,"ft_is_entry":true},{"amount":0.024,"safe_price":19893.25571114223,"ft_order_side":"sell","order_filled_timestamp":1664856000000,"ft_is_entry":false}]},{"pair":"BTC/USDT","stake_amount":465.0324,"amount":0.023,"open_date":"2022-10-05 08:00:00+00:00","close_date":"2022-10-25 16:00:00+00:00","open_rate":20218.8,"close_rate":20226.889137827566,"fee_open":0.0002,"fee_close":0.0002,"trade_duration":29280,"profit_ratio":-0.003819304160234872,"profit_abs":-1.7764554,"exit_reason":"roi","initial_stop_loss_abs":15042.8,"initial_stop_loss_ratio":-0.256,"stop_loss_abs":15042.8,"stop_loss_ratio":-0.256,"min_rate":17917.8,"max_rate":20443.9,"is_open":false,"enter_tag":null,"leverage":1.0,"is_short":false,"open_timestamp":1664956800000,"close_timestamp":1666713600000,"orders":[{"amount":0.023,"safe_price":20218.8,"ft_order_side":"buy","order_filled_timestamp":1664956800000,"ft_is_entry":true},{"amount":0.023,"safe_price":20226.889137827566,"ft_order_side":"sell","order_filled_timestamp":1666713600000,"ft_is_entry":false}]},{"pair":"BTC/USDT","stake_amount":466.1341,"amount":0.023,"open_date":"2022-10-25 20:00:00+00:00","close_date":"2022-10-31 00:00:00+00:00","open_rate":20266.7,"close_rate":20416.0,"fee_open":0.0002,"fee_close":0.0002,"trade_duration":7440,"profit_ratio":0.0066426807307150455,"profit_abs":3.09699928,"exit_reason":"roi","initial_stop_loss_abs":15078.5,"initial_stop_loss_ratio":-0.256,"stop_loss_abs":15078.5,"stop_loss_ratio":-0.256,"min_rate":19951.0,"max_rate":21088.0,"is_open":false,"enter_tag":null,"leverage":1.0,"is_short":false,"open_timestamp":1666728000000,"close_timestamp":1667174400000,"orders":[{"amount":0.023,"safe_price":20266.7,"ft_order_side":"buy","order_filled_timestamp":1666728000000,"ft_is_entry":true},{"amount":0.023,"safe_price":20416.0,"ft_order_side":"sell","order_filled_timestamp":1667174400000,"ft_is_entry":false}]},{"pair":"BTC/USDT","stake_amount":471.6794,"amount":0.023,"open_date":"2022-10-31 04:00:00+00:00","close_date":"2022-11-05 08:00:00+00:00","open_rate":20507.8,"close_rate":21226.8,"fee_open":0.0002,"fee_close":0.0002,"trade_duration":7440,"profit_ratio":0.034165441808528006,"profit_abs":16.11835812,"exit_reason":"roi","initial_stop_loss_abs":15257.9,"initial_stop_loss_ratio":-0.256,"stop_loss_abs":15257.9,"stop_loss_ratio":-0.256,"min_rate":20026.0,"max_rate":21473.7,"is_open":false,"enter_tag":null,"leverage":1.0,"is_short":false,"open_timestamp":1667188800000,"close_timestamp":1667635200000,"orders":[{"amount":0.023,"safe_price":20507.8,"ft_order_side":"buy","order_filled_timestamp":1667188800000,"ft_is_entry":true},{"amount":0.023,"safe_price":21226.8,"ft_order_side":"sell","order_filled_timestamp":1667635200000,"ft_is_entry":false}]},{"pair":"BTC/USDT","stake_amount":489.6631,"amount":0.023,"open_date":"2022-11-05 16:00:00+00:00","close_date":"2022-11-09 20:00:00+00:00","open_rate":21289.7,"close_rate":15839.6,"fee_open":0.0002,"fee_close":0.0002,"trade_duration":6000,"profit_ratio":-0.25671477946582905,"profit_abs":-125.72889548,"exit_reason":"stop_loss","initial_stop_loss_abs":15839.6,"initial_stop_loss_ratio":-0.256,"stop_loss_abs":15839.6,"stop_loss_ratio":-0.256,"min_rate":15462.6,"max_rate":21373.1,"is_open":false,"enter_tag":null,"leverage":1.0,"is_short":false,"open_timestamp":1667664000000,"close_timestamp":1668024000000,"orders":[{"amount":0.023,"safe_price":21289.7,"ft_order_side":"buy","order_filled_timestamp":1667664000000,"ft_is_entry":true},{"amount":0.023,"safe_price":15839.6,"ft_order_side":"sell","order_filled_timestamp":1668024000000,"ft_is_entry":false}]},{"pair":"BTC/USDT","stake_amount":364.056,"amount":0.022,"open_date":"2022-11-16 20:00:00+00:00","close_date":"2022-11-23 00:00:00+00:00","open_rate":16548.0,"close_rate":16554.620524104823,"fee_open":0.0002,"fee_close":0.0002,"trade_duration":8880,"profit_ratio":-0.00022849823315491605,"profit_abs":-0.08320279,"exit_reason":"roi","initial_stop_loss_abs":12311.8,"initial_stop_loss_ratio":-0.256,"stop_loss_abs":12311.8,"stop_loss_ratio":-0.256,"min_rate":15443.2,"max_rate":16984.4,"is_open":false,"enter_tag":null,"leverage":1.0,"is_short":false,"open_timestamp":1668628800000,"close_timestamp":1669161600000,"orders":[{"amount":0.022,"safe_price":16548.0,"ft_order_side":"buy","order_filled_timestamp":1668628800000,"ft_is_entry":true},{"amount":0.022,"safe_price":16554.620524104823,"ft_order_side":"sell","order_filled_timestamp":1669161600000,"ft_is_entry":false}]},{"pair":"BTC/USDT","stake_amount":362.5644,"amount":0.022,"open_date":"2022-11-25 04:00:00+00:00","close_date":"2022-11-29 16:00:00+00:00","open_rate":16480.2,"close_rate":16384.9,"fee_open":0.0002,"fee_close":0.0002,"trade_duration":6480,"profit_ratio":-0.00633669311750512,"profit_abs":-2.29791883,"exit_reason":"force_exit","initial_stop_loss_abs":12261.3,"initial_stop_loss_ratio":-0.256,"stop_loss_abs":12261.3,"stop_loss_ratio":-0.256,"min_rate":15984.1,"max_rate":16699.1,"is_open":false,"enter_tag":null,"leverage":1.0,"is_short":false,"open_timestamp":1669348800000,"close_timestamp":1669737600000,"orders":[{"amount":0.022,"safe_price":16480.2,"ft_order_side":"buy","order_filled_timestamp":1669348800000,"ft_is_entry":true},{"amount":0.022,"safe_price":16384.9,"ft_order_side":"sell","order_filled_timestamp":1669737600000,"ft_is_entry":false}]}],"locks":[],"best_pair":{"key":"BTC/USDT","trades":26,"profit_mean":-0.032465952738567866,"profit_mean_pct":-3.2465952738567867,"profit_sum":-0.8441147712027646,"profit_sum_pct":-84.41,"profit_total_abs":-623.3928640499998,"profit_total":-0.6233928640499998,"profit_total_pct":-62.34,"duration_avg":"10 days, 22:37:00","wins":7,"draws":0,"losses":19},"worst_pair":{"key":"BTC/USDT","trades":26,"profit_mean":-0.032465952738567866,"profit_mean_pct":-3.2465952738567867,"profit_sum":-0.8441147712027646,"profit_sum_pct":-84.41,"profit_total_abs":-623.3928640499998,"profit_total":-0.6233928640499998,"profit_total_pct":-62.34,"duration_avg":"10 days, 22:37:00","wins":7,"draws":0,"losses":19},"results_per_pair":[{"key":"BTC/USDT","trades":26,"profit_mean":-0.032465952738567866,"profit_mean_pct":-3.2465952738567867,"profit_sum":-0.8441147712027646,"profit_sum_pct":-84.41,"profit_total_abs":-623.3928640499998,"profit_total":-0.6233928640499998,"profit_total_pct":-62.34,"duration_avg":"10 days, 22:37:00","wins":7,"draws":0,"losses":19},{"key":"TOTAL","trades":26,"profit_mean":-0.032465952738567866,"profit_mean_pct":-3.2465952738567867,"profit_sum":-0.8441147712027646,"profit_sum_pct":-84.41,"profit_total_abs":-623.3928640499998,"profit_total":-0.6233928640499998,"profit_total_pct":-62.34,"duration_avg":"10 days, 22:37:00","wins":7,"draws":0,"losses":19}],"results_per_enter_tag":[{"key":"TOTAL","trades":26,"profit_mean":-0.032465952738567866,"profit_mean_pct":-3.2465952738567867,"profit_sum":-0.8441147712027646,"profit_sum_pct":-84.41,"profit_total_abs":-623.3928640499998,"profit_total":-0.6233928640499998,"profit_total_pct":-62.34,"duration_avg":"10 days, 22:37:00","wins":7,"draws":0,"losses":19}],"exit_reason_summary":[{"exit_reason":"roi","trades":21,"wins":7,"draws":0,"losses":14,"profit_mean":0.009281662865939563,"profit_mean_pct":0.93,"profit_sum":0.1949149201847308,"profit_sum_pct":19.49,"profit_total_abs":131.3817671,"profit_total":0.1949149201847308,"profit_total_pct":19.49},{"exit_reason":"stop_loss","trades":4,"wins":0,"draws":0,"losses":4,"profit_mean":-0.2581732495674976,"profit_mean_pct":-25.82,"profit_sum":-1.0326929982699904,"profit_sum_pct":-103.27,"profit_total_abs":-752.47671232,"profit_total":-1.0326929982699904,"profit_total_pct":-103.27},{"exit_reason":"force_exit","trades":1,"wins":0,"draws":0,"losses":1,"profit_mean":-0.00633669311750512,"profit_mean_pct":-0.63,"profit_sum":-0.00633669311750512,"profit_sum_pct":-0.63,"profit_total_abs":-2.29791883,"profit_total":-0.00633669311750512,"profit_total_pct":-0.63}],"left_open_trades":[{"key":"BTC/USDT","trades":1,"profit_mean":-0.00633669311750512,"profit_mean_pct":-0.633669311750512,"profit_sum":-0.00633669311750512,"profit_sum_pct":-0.63,"profit_total_abs":-2.29791883,"profit_total":-0.00229791883,"profit_total_pct":-0.23,"duration_avg":"4 days, 12:00:00","wins":0,"draws":0,"losses":1},{"key":"TOTAL","trades":1,"profit_mean":-0.00633669311750512,"profit_mean_pct":-0.633669311750512,"profit_sum":-0.00633669311750512,"profit_sum_pct":-0.63,"profit_total_abs":-2.29791883,"profit_total":-0.00229791883,"profit_total_pct":-0.23,"duration_avg":"4 days, 12:00:00","wins":0,"draws":0,"losses":1}],"total_trades":26,"trade_count_long":26,"trade_count_short":0,"total_volume":17903.69618,"avg_stake_amount":688.6036992307692,"profit_mean":-0.032465952738567866,"profit_median":-0.0013435172521114988,"profit_total":-0.6233928640499998,"profit_total_long":-0.6233928640499998,"profit_total_short":0.0,"profit_total_abs":-623.3928640499998,"profit_total_long_abs":-623.3928640499998,"profit_total_short_abs":0.0,"cagr":-0.6582308265686416,"profit_factor":0.19071319592866892,"backtest_start":"2022-01-01 00:00:00","backtest_start_ts":1640995200000,"backtest_end":"2022-11-29 16:00:00","backtest_end_ts":1669737600000,"backtest_days":332,"backtest_run_start_ts":1669782974,"backtest_run_end_ts":1669782974,"trades_per_day":0.08,"market_change":-0.6491054842148547,"pairlist":["BTC/USDT"],"stake_amount":"unlimited","stake_currency":"USDT","stake_currency_decimals":3,"starting_balance":1000,"dry_run_wallet":1000,"final_balance":376.60713594999993,"rejected_signals":0,"timedout_entry_orders":0,"timedout_exit_orders":0,"canceled_trade_entries":0,"canceled_entry_orders":0,"replaced_entry_orders":0,"max_open_trades":1,"max_open_trades_setting":1,"timeframe":"4h","timeframe_detail":"","timerange":"","enable_protections":false,"strategy_name":"Heracles","stoploss":-0.256,"trailing_stop":false,"trailing_stop_positive":null,"trailing_stop_positive_offset":0.0,"trailing_only_offset_is_reached":false,"use_custom_stoploss":false,"minimal_roi":{"0":0.598,"644":0.166,"3269":0.115,"7289":0},"use_exit_signal":true,"exit_profit_only":false,"exit_profit_offset":0.0,"ignore_roi_if_entry_signal":false,"backtest_best_day":0.05143362743075863,"backtest_worst_day":-0.2594192790115727,"backtest_best_day_abs":49.92909666,"backtest_worst_day_abs":-264.10438374,"winning_days":7,"draw_days":296,"losing_days":19,"daily_profit":[["2022-01-12",-1.63450217],["2022-01-13",0.0],["2022-01-14",0.0],["2022-01-15",0.0],["2022-01-16",0.0],["2022-01-17",0.0],["2022-01-18",0.0],["2022-01-19",0.0],["2022-01-20",0.0],["2022-01-21",0.0],["2022-01-22",0.0],["2022-01-23",0.0],["2022-01-24",0.0],["2022-01-25",0.0],["2022-01-26",0.0],["2022-01-27",0.0],["2022-01-28",0.0],["2022-01-29",0.0],["2022-01-30",0.0],["2022-01-31",0.0],["2022-02-01",0.0],["2022-02-02",0.0],["2022-02-03",0.0],["2022-02-04",0.0],["2022-02-05",0.0],["2022-02-06",0.0],["2022-02-07",-2.18212749],["2022-02-08",0.0],["2022-02-09",0.0],["2022-02-10",0.0],["2022-02-11",0.0],["2022-02-12",0.0],["2022-02-13",0.0],["2022-02-14",0.0],["2022-02-15",-1.16286739],["2022-02-16",0.0],["2022-02-17",0.0],["2022-02-18",0.0],["2022-02-19",0.0],["2022-02-20",0.0],["2022-02-21",0.0],["2022-02-22",0.0],["2022-02-23",0.0],["2022-02-24",0.0],["2022-02-25",0.0],["2022-02-26",0.0],["2022-02-27",0.0],["2022-02-28",0.0],["2022-03-01",-0.68555019],["2022-03-02",0.0],["2022-03-03",0.0],["2022-03-04",0.0],["2022-03-05",0.0],["2022-03-06",0.0],["2022-03-07",0.0],["2022-03-08",0.0],["2022-03-09",0.0],["2022-03-10",0.0],["2022-03-11",0.0],["2022-03-12",0.0],["2022-03-13",0.0],["2022-03-14",0.0],["2022-03-15",0.0],["2022-03-16",0.0],["2022-03-17",0.0],["2022-03-18",0.0],["2022-03-19",0.0],["2022-03-20",0.0],["2022-03-21",0.0],["2022-03-22",-2.38628758],["2022-03-23",0.0],["2022-03-24",0.0],["2022-03-25",0.0],["2022-03-26",0.0],["2022-03-27",49.92909666],["2022-03-28",0.0],["2022-03-29",0.0],["2022-03-30",0.0],["2022-03-31",0.0],["2022-04-01",25.97161557],["2022-04-02",0.0],["2022-04-03",0.0],["2022-04-04",0.0],["2022-04-05",0.0],["2022-04-06",0.0],["2022-04-07",0.0],["2022-04-08",0.0],["2022-04-09",0.0],["2022-04-10",0.0],["2022-04-11",0.0],["2022-04-12",0.0],["2022-04-13",0.0],["2022-04-14",0.0],["2022-04-15",0.0],["2022-04-16",0.0],["2022-04-17",0.0],["2022-04-18",0.0],["2022-04-19",0.0],["2022-04-20",0.0],["2022-04-21",0.0],["2022-04-22",0.0],["2022-04-23",0.0],["2022-04-24",0.0],["2022-04-25",0.0],["2022-04-26",0.0],["2022-04-27",0.0],["2022-04-28",0.0],["2022-04-29",0.0],["2022-04-30",0.0],["2022-05-01",0.0],["2022-05-02",0.0],["2022-05-03",0.0],["2022-05-04",0.0],["2022-05-05",0.0],["2022-05-06",0.0],["2022-05-07",0.0],["2022-05-08",-264.10438374],["2022-05-09",0.0],["2022-05-10",0.0],["2022-05-11",0.0],["2022-05-12",0.0],["2022-05-13",0.0],["2022-05-14",0.0],["2022-05-15",0.0],["2022-05-16",0.0],["2022-05-17",0.0],["2022-05-18",0.0],["2022-05-19",0.0],["2022-05-20",0.0],["2022-05-21",0.0],["2022-05-22",0.0],["2022-05-23",-0.40735301],["2022-05-24",0.0],["2022-05-25",0.0],["2022-05-26",0.0],["2022-05-27",0.0],["2022-05-28",0.0],["2022-05-29",0.0],["2022-05-30",-1.10891685],["2022-05-31",0.0],["2022-06-01",0.0],["2022-06-02",0.0],["2022-06-03",0.0],["2022-06-04",0.0],["2022-06-05",0.0],["2022-06-06",0.0],["2022-06-07",0.0],["2022-06-08",0.0],["2022-06-09",0.0],["2022-06-10",0.0],["2022-06-11",0.0],["2022-06-12",0.0],["2022-06-13",-205.11455808],["2022-06-14",0.0],["2022-06-15",0.0],["2022-06-16",0.0],["2022-06-17",0.0],["2022-06-18",0.0],["2022-06-19",0.0],["2022-06-20",0.0],["2022-06-21",0.0],["2022-06-22",0.0],["2022-06-23",0.0],["2022-06-24",0.0],["2022-06-25",0.0],["2022-06-26",0.0],["2022-06-27",0.0],["2022-06-28",0.0],["2022-06-29",0.0],["2022-06-30",0.0],["2022-07-01",0.0],["2022-07-02",0.0],["2022-07-03",0.0],["2022-07-04",0.0],["2022-07-05",0.0],["2022-07-06",0.0],["2022-07-07",-0.60393313],["2022-07-08",0.0],["2022-07-09",0.0],["2022-07-10",0.0],["2022-07-11",0.0],["2022-07-12",0.0],["2022-07-13",0.0],["2022-07-14",0.0],["2022-07-15",0.0],["2022-07-16",0.0],["2022-07-17",0.0],["2022-07-18",-1.07283445],["2022-07-19",0.0],["2022-07-20",0.0],["2022-07-21",0.0],["2022-07-22",0.0],["2022-07-23",-0.85421788],["2022-07-24",0.0],["2022-07-25",0.0],["2022-07-26",0.0],["2022-07-27",0.0],["2022-07-28",0.0],["2022-07-29",0.0],["2022-07-30",26.39509137],["2022-07-31",0.0],["2022-08-01",0.0],["2022-08-02",0.0],["2022-08-03",0.0],["2022-08-04",0.0],["2022-08-05",0.0],["2022-08-06",0.0],["2022-08-07",0.0],["2022-08-08",-0.95072622],["2022-08-09",0.0],["2022-08-10",0.0],["2022-08-11",0.0],["2022-08-12",0.0],["2022-08-13",3.3036888],["2022-08-14",0.0],["2022-08-15",0.0],["2022-08-16",0.0],["2022-08-17",0.0],["2022-08-18",0.0],["2022-08-19",0.0],["2022-08-20",0.0],["2022-08-21",0.0],["2022-08-22",0.0],["2022-08-23",0.0],["2022-08-24",0.0],["2022-08-25",0.0],["2022-08-26",0.0],["2022-08-27",0.0],["2022-08-28",0.0],["2022-08-29",0.0],["2022-08-30",0.0],["2022-08-31",0.0],["2022-09-01",0.0],["2022-09-02",0.0],["2022-09-03",0.0],["2022-09-04",0.0],["2022-09-05",0.0],["2022-09-06",0.0],["2022-09-07",0.0],["2022-09-08",0.0],["2022-09-09",0.0],["2022-09-10",0.0],["2022-09-11",0.0],["2022-09-12",0.0],["2022-09-13",0.0],["2022-09-14",0.0],["2022-09-15",0.0],["2022-09-16",0.0],["2022-09-17",0.0],["2022-09-18",0.0],["2022-09-19",0.0],["2022-09-20",0.0],["2022-09-21",-157.52887502],["2022-09-22",0.0],["2022-09-23",0.0],["2022-09-24",0.0],["2022-09-25",0.0],["2022-09-26",0.0],["2022-09-27",22.09134566],["2022-09-28",0.0],["2022-09-29",0.0],["2022-09-30",0.0],["2022-10-01",0.0],["2022-10-02",0.0],["2022-10-03",0.0],["2022-10-04",-0.61545381],["2022-10-05",0.0],["2022-10-06",0.0],["2022-10-07",0.0],["2022-10-08",0.0],["2022-10-09",0.0],["2022-10-10",0.0],["2022-10-11",0.0],["2022-10-12",0.0],["2022-10-13",0.0],["2022-10-14",0.0],["2022-10-15",0.0],["2022-10-16",0.0],["2022-10-17",0.0],["2022-10-18",0.0],["2022-10-19",0.0],["2022-10-20",0.0],["2022-10-21",0.0],["2022-10-22",0.0],["2022-10-23",0.0],["2022-10-24",0.0],["2022-10-25",-1.7764554],["2022-10-26",0.0],["2022-10-27",0.0],["2022-10-28",0.0],["2022-10-29",0.0],["2022-10-30",0.0],["2022-10-31",3.09699928],["2022-11-01",0.0],["2022-11-02",0.0],["2022-11-03",0.0],["2022-11-04",0.0],["2022-11-05",16.11835812],["2022-11-06",0.0],["2022-11-07",0.0],["2022-11-08",0.0],["2022-11-09",-125.72889548],["2022-11-10",0.0],["2022-11-11",0.0],["2022-11-12",0.0],["2022-11-13",0.0],["2022-11-14",0.0],["2022-11-15",0.0],["2022-11-16",0.0],["2022-11-17",0.0],["2022-11-18",0.0],["2022-11-19",0.0],["2022-11-20",0.0],["2022-11-21",0.0],["2022-11-22",0.0],["2022-11-23",-0.08320279],["2022-11-24",0.0],["2022-11-25",0.0],["2022-11-26",0.0],["2022-11-27",0.0],["2022-11-28",0.0],["2022-11-29",-2.29791883]],"wins":7,"losses":19,"draws":0,"holding_avg":"10 days, 22:37:00","holding_avg_s":945420.0,"winner_holding_avg":"5 days, 4:00:00","winner_holding_avg_s":446400.0,"loser_holding_avg":"13 days, 1:41:00","loser_holding_avg_s":1129260.0,"max_drawdown":0.9123390979903413,"max_drawdown_account":0.6473218565117898,"max_relative_drawdown":0.6473218565117898,"max_drawdown_abs":691.2422414600001,"drawdown_start":"2022-04-01 20:00:00","drawdown_start_ts":1648843200000.0,"drawdown_end":"2022-11-29 16:00:00","drawdown_end_ts":1669737600000.0,"max_drawdown_low":-623.3928640500001,"max_drawdown_high":67.84937741,"csum_min":376.60713594999993,"csum_max":1067.84937741}},"strategy_comparison":[{"key":"Heracles","trades":26,"profit_mean":-0.032465952738567866,"profit_mean_pct":-3.2465952738567867,"profit_sum":-0.8441147712027646,"profit_sum_pct":-84.41,"profit_total_abs":-623.3928640499998,"profit_total":-0.6233928640499998,"profit_total_pct":-62.34,"duration_avg":"10 days, 22:37:00","wins":7,"draws":0,"losses":19,"max_drawdown_account":0.6473218565117898,"max_drawdown_abs":"691.242"}]}